MANIFEST.in
README.md
setup.py
Confopy.egg-info/PKG-INFO
Confopy.egg-info/SOURCES.txt
Confopy.egg-info/dependency_links.txt
Confopy.egg-info/requires.txt
Confopy.egg-info/top_level.txt
bin/confopy
confopy/__init__.py
confopy/__main__.py
confopy/config.py
confopy/analysis/__init__.py
confopy/analysis/analyzer.py
confopy/analysis/corpus.py
confopy/analysis/localizable.py
confopy/analysis/metric.py
confopy/analysis/report.py
confopy/analysis/rule.py
confopy/analysis/spellcheck.py
confopy/analysis/statistics.py
confopy/localization/__init__.py
confopy/localization/de/__init__.py
confopy/localization/de/corpus.py
confopy/localization/de/metrics.py
confopy/localization/de/reports.py
confopy/localization/de/rules.py
confopy/localization/de/corpus_de/__init__.py
confopy/localization/de/corpus_de/fillers_de.py
confopy/localization/de/corpus_de/tiger.py
confopy/localization/de/corpus_de/tiger_dl_patch.py
confopy/localization/de/corpus_de/tiger_release_aug07.corrected.16012013_patch.py
confopy/model/__init__.py
confopy/model/confopy_document.xsd
confopy/model/document.py
confopy/model/document_converter.py
confopy/model/lines.py
confopy/model/validate.py
confopy/pdfextract/__init__.py
confopy/pdfextract/__main__.py
confopy/pdfextract/_pdf2txt.py
confopy/pdfextract/convenience.py
confopy/pdfextract/heuristics.py
confopy/pdfextract/pdfminer_wrapper.py
confopy/pdfextract/pdfminer_xml_bindings.py
confopy/pdfextract/xml_util.py