Metadata-Version: 1.0
Name: Confopy
Version: 0.4.10
Summary: Evaluates the linguistic and structural quality of scientific texts.
Home-page: https://github.com/ooz/Confopy
Author: Oliver Zscheyge
Author-email: oliverzscheyge@gmail.com
License: MIT License
Platform: UNKNOWN
